assistant/__init__.py
assistant/assistant.py
assistant/eventable.py
assistant/transcriber.py
simple_virtual_assistant-0.0.5.dist-info/licenses/LICENSE
simple_virtual_assistant-0.0.5.dist-info/METADATA
simple_virtual_assistant-0.0.5.dist-info/WHEEL
simple_virtual_assistant-0.0.5.dist-info/top_level.txt
simple_virtual_assistant-0.0.5.dist-info/RECORD
