Metadata-Version: 2.4
Name: simple-virtual-assistant
Version: 0.0.5
Summary: A simple voice assistant meant to be easily extensible.
Author-email: Anthony Maranto <author@example.com>
Project-URL: Homepage, https://github.com/atmaranto/VoiceAssistant
Project-URL: Issues, https://github.com/atmaranto/VoiceAssistant/issues
Classifier: Programming Language :: Python :: 3
Classifier: Operating System :: OS Independent
Requires-Python: >=3.9
License-File: LICENSE
Dynamic: license-file
